{
    "tenantId": "pg",
    "moduleName": "FSM",
    "FSTPPlantInfo": [
        {
            "PlantCode": "CTA001",
            "PlantName": "CityA FSTP",
            "active": true,
            "PlantType":"FSTP",
            "PlantLocation":"CityA",
            "latitude":"12.976746" ,
            "longitude":"77.575278",
            "PlusCode":"VM3C+VQM Bengaluru, Karnataka",
            "PlantOperationalTimings":"10.00am-08.00pm",
            "PlantOperationalCapacityKLD":"50",
            "ULBS":"pg.citya"
        },
        {
            "PlantCode": "CTB001",
            "PlantName": "CityB SeTPP",
            "active": true,
            "PlantType":"SeTP",
            "PlantLocation":"CityB",
            "latitude":"12.9292015" ,
            "longitude":"77.6212001",
            "PlusCode":"MPFQ+V2 Sahibzada Ajit Singh Nagar, Punjab",
            "PlantOperationalTimings":"10.00am-06.00pm",
            "PlantOperationalCapacityKLD":"100",
            "ULBS":"pg.cityb"
        }
    ]
}
